pypsea/__init__.py
pypsea/_version.py
pypsea/example.py
pypsea/nbextension/__init__.py
pypsea/tests/__init__.py
pypsea/tests/conftest.py
pypsea/tests/test_example.py
pypsea/tests/test_nbextension_path.py
pypsea-0.0.1.dist-info/DESCRIPTION.rst
pypsea-0.0.1.dist-info/METADATA
pypsea-0.0.1.dist-info/RECORD
pypsea-0.0.1.dist-info/WHEEL
pypsea-0.0.1.dist-info/metadata.json
pypsea-0.0.1.dist-info/top_level.txt
