Metadata-Version: 2.0
Name: pypsea
Version: 0.0.1
Summary: Protein Set Enrichment Analysis (PSEA) in a Python wrapper.
Home-page: https://github.com/draperjames/pypsea
Author: James Draper
Author-email: james.draper@duke.edu
License: MIT
Keywords: Jupyter Notebook
Platform: UNKNOWN
Classifier: Development Status :: 3 - Alpha
Classifier: Intended Audience :: Developers
Classifier: Topic :: Software Development :: Build Tools
Classifier: License :: OSI Approved :: MIT License
Classifier: Programming Language :: Python :: 3.4
Classifier: Programming Language :: Python :: 3.5
Classifier: Programming Language :: Python :: 3.6
Requires-Dist: pandas
Requires-Dist: xlrd
